wylog/__init__.py
wylog/logging.py
wylog/multi.py
wylog-1.0.0.dist-info/DESCRIPTION.rst
wylog-1.0.0.dist-info/METADATA
wylog-1.0.0.dist-info/RECORD
wylog-1.0.0.dist-info/WHEEL
wylog-1.0.0.dist-info/metadata.json
wylog-1.0.0.dist-info/top_level.txt
