Metadata-Version: 2.0
Name: wylog
Version: 1.0.0
Summary: A collection of simple logging methods
Home-page: https://github.com/Wyko/wylog
Author: Wyko ter Haar
Author-email: vegaswyko@gmail.com
License: MIT
Keywords: logging
Platform: UNKNOWN
Classifier: Development Status :: 3 - Alpha
Classifier: Topic :: Utilities
Classifier: License :: OSI Approved :: MIT License
